LICENSE.txt
README.md
setup.py
src/datajs/__init__.py
src/datajs.egg-info/PKG-INFO
src/datajs.egg-info/SOURCES.txt
src/datajs.egg-info/dependency_links.txt
src/datajs.egg-info/top_level.txt